<?xml version="1.0" encoding="UTF-8"?>
<!DOCTYPE mapper PUBLIC "-//mybatis.org//DTD Mapper 3.0//EN" "http://mybatis.org/dtd/mybatis-3-mapper.dtd">
<mapper namespace="com.hzdongcheng.softwareplatform.intelligentstorage.dal.dao.custom.mapper.TerminalExDao">
  <resultMap id="BaseResultMap" type="com.hzdongcheng.softwareplatform.intelligentstorage.dal.dao.custom.entity.TerminalEx">
    <!--
      WARNING - @mbg.generated
      This element is automatically generated by MyBatis Generator, do not modify.
    -->
    <id column="terminalID" jdbcType="VARCHAR" property="terminalid" />
    <result column="areaCode" jdbcType="VARCHAR" property="areacode" />
    <result column="displayName" jdbcType="VARCHAR" property="displayname" />
    <result column="totalBoxNumber" jdbcType="INTEGER" property="totalboxnumber" />
    <result column="businessCode" jdbcType="INTEGER" property="businesscode" />
    <result column="Address" jdbcType="VARCHAR" property="address" />
    <result column="IpAddr" jdbcType="VARCHAR" property="ipaddr" />
    <result column="macAddress" jdbcType="VARCHAR" property="macaddress" />
    <result column="runStatus" jdbcType="TINYINT" property="runstatus" />
    <result column="networkState" jdbcType="TINYINT" property="networkstate" />
    <result column="version" jdbcType="VARCHAR" property="version" />
    <result column="longitode" jdbcType="VARCHAR" property="longitode" />
    <result column="dimension" jdbcType="VARCHAR" property="dimension" />
    <result column="registerFlag" jdbcType="VARCHAR" property="registerflag" />
    <result column="makeOpCode" jdbcType="VARCHAR" property="makeopcode" />
    <result column="makeDate" jdbcType="TIMESTAMP" property="makedate" />
    <result column="lastModifyTime" jdbcType="TIMESTAMP" property="lastmodifytime" />
    <result column="memo" jdbcType="VARCHAR" property="memo" />
    <result column="boxCode" jdbcType="VARCHAR" property="boxcode" />
    <result column="numbering" jdbcType="INTEGER" property="numbering" />
    <result column="longitude" jdbcType="VARCHAR" property="longitude" />
    <result column="latitude" jdbcType="VARCHAR" property="latitude" />
    <result column="dumpEnergy" jdbcType="VARCHAR" property="dumpenergy" />
    <result column="appKey" jdbcType="VARCHAR" property="appkey" />
    <association property="areaEntity" column="areacode" javaType="AreaEntity" select="findAreaEntityById"/>
    <association property="businessEntity" column="businesscode" javaType="BusinessModelEntity" select="findbusinessEntityById"/>
  </resultMap>
  
  <resultMap id="AreaResultMap" type="AreaEntity">
    <id column="areaCode" jdbcType="VARCHAR" property="areacode" />
    <result column="areaName" jdbcType="VARCHAR" property="areaname" />
    <result column="areaShortName" jdbcType="VARCHAR" property="areashortname" />
  </resultMap>
  <resultMap id="BusinessResultMap" type="BusinessModelEntity">
    <id column="businessCode" jdbcType="VARCHAR" property="businesscode" />
    <result column="businessName" jdbcType="VARCHAR" property="businessname" />
  </resultMap>
  
  <sql id="Example_Where_Clause">
    <!--
      WARNING - @mbg.generated
      This element is automatically generated by MyBatis Generator, do not modify.
    -->
    <where>
      <foreach collection="oredCriteria" item="criteria" separator="or">
        <if test="criteria.valid">
          <trim prefix="(" prefixOverrides="and" suffix=")">
            <foreach collection="criteria.criteria" item="criterion">
              <choose>
                <when test="criterion.noValue">
                  and ${criterion.condition}
                </when>
                <when test="criterion.singleValue">
                  and ${criterion.condition} #{criterion.value}
                </when>
                <when test="criterion.betweenValue">
                  and ${criterion.condition} #{criterion.value} and #{criterion.secondValue}
                </when>
                <when test="criterion.listValue">
                  and ${criterion.condition}
                  <foreach close=")" collection="criterion.value" item="listItem" open="(" separator=",">
                    #{listItem}
                  </foreach>
                </when>
              </choose>
            </foreach>
          </trim>
        </if>
      </foreach>
    </where>
  </sql>
  <sql id="Update_By_Example_Where_Clause">
    <!--
      WARNING - @mbg.generated
      This element is automatically generated by MyBatis Generator, do not modify.
    -->
    <where>
      <foreach collection="example.oredCriteria" item="criteria" separator="or">
        <if test="criteria.valid">
          <trim prefix="(" prefixOverrides="and" suffix=")">
            <foreach collection="criteria.criteria" item="criterion">
              <choose>
                <when test="criterion.noValue">
                  and ${criterion.condition}
                </when>
                <when test="criterion.singleValue">
                  and ${criterion.condition} #{criterion.value}
                </when>
                <when test="criterion.betweenValue">
                  and ${criterion.condition} #{criterion.value} and #{criterion.secondValue}
                </when>
                <when test="criterion.listValue">
                  and ${criterion.condition}
                  <foreach close=")" collection="criterion.value" item="listItem" open="(" separator=",">
                    #{listItem}
                  </foreach>
                </when>
              </choose>
            </foreach>
          </trim>
        </if>
      </foreach>
    </where>
  </sql>
  <sql id="Base_Column_List">
    <!--
      WARNING - @mbg.generated
      This element is automatically generated by MyBatis Generator, do not modify.
    -->
    terminalID, areaCode, displayName, totalBoxNumber, businessCode, Address, IpAddr, 
    macAddress, runStatus, networkState, version, longitode, dimension, registerFlag, 
    makeOpCode, makeDate, lastModifyTime, memo, boxCode, numbering , longitude, latitude,  dumpEnergy, appKey
  </sql>
  
  <select id="selectByExampleEx" parameterType="com.hzdongcheng.softwareplatform.intelligentstorage.dal.dao.table.entity.TerminalEntityExample" resultMap="BaseResultMap">
    <!--
      WARNING - @mbg.generated
      This element is automatically generated by MyBatis Generator, do not modify.
    -->
    select
    <if test="distinct">
      distinct
    </if>
    <include refid="Base_Column_List" />
    from terminal
    <if test="_parameter != null">
      <include refid="Example_Where_Clause" />
    </if>
    <if test="orderByClause != null">
      order by ${orderByClause}
    </if>
  </select>
  <select id="selectAllBycode" parameterType="java.lang.Integer" resultMap="BaseResultMap">
  	select * from terminal where businessCode=#{code};
  </select>
  <select id="findAreaEntityById" parameterType="java.lang.String" resultMap="AreaResultMap">
  	select * from Area where areacode=#{id};
  </select>
  <select id="findbusinessEntityById" parameterType="java.lang.String" resultMap="BusinessResultMap">
  	select DISTINCT(businessName) from businessmodel where businesscode=#{id};
  </select>
</mapper>